lbx_toolkit/__init__.py
lbx_toolkit-2.0.0.dist-info/LICENSE
lbx_toolkit-2.0.0.dist-info/METADATA
lbx_toolkit-2.0.0.dist-info/WHEEL
lbx_toolkit-2.0.0.dist-info/top_level.txt
lbx_toolkit-2.0.0.dist-info/RECORD
