Metadata-Version: 2.1
Name: lbx_toolkit
Version: 2.0.0
Summary: Biblioteca de ferramentas LBX S/A
Author: Cristiano P. Ferrari
Author-email: boxferrari@gmail.com
License: MIT License
Classifier: Programming Language :: Python :: 3
Classifier: License :: OSI Approved :: MIT License
Classifier: Operating System :: OS Independent
Requires-Python: >=3.6
License-File: LICENSE
Requires-Dist: psycopg2
Requires-Dist: pandas
Requires-Dist: numpy
Requires-Dist: msal
Requires-Dist: requests
Requires-Dist: selenium
Requires-Dist: webdriver-manager
Requires-Dist: validators
